pydmt/__init__.py
pydmt/configs.py
pydmt/main.py
pydmt/static.py
pydmt/api/__init__.py
pydmt/api/builder.py
pydmt/api/copy.py
pydmt/api/fail.py
pydmt/api/feature.py
pydmt/api/one_source_one_target.py
pydmt/builders/__init__.py
pydmt/builders/apt.py
pydmt/builders/copy.py
pydmt/builders/gem.py
pydmt/builders/make.py
pydmt/builders/mako.py
pydmt/builders/npm.py
pydmt/builders/reqs.py
pydmt/builders/sphinx.py
pydmt/builders/venv.py
pydmt/builders/yaml.py
pydmt/core/__init__.py
pydmt/core/cache.py
pydmt/core/graph.py
pydmt/core/pydmt.py
pydmt/core/tempdir.py
pydmt/features/__init__.py
pydmt/features/apt.py
pydmt/features/gem.py
pydmt/features/make.py
pydmt/features/mako.py
pydmt/features/npm.py
pydmt/features/reqs.py
pydmt/features/sphinx.py
pydmt/features/venv.py
pydmt/features/yaml.py
pydmt/helpers/__init__.py
pydmt/helpers/apt.py
pydmt/helpers/attrs.py
pydmt/helpers/composites.py
pydmt/helpers/deb_python_package.py
pydmt/helpers/files.py
pydmt/helpers/general.py
pydmt/helpers/git.py
pydmt/helpers/github.py
pydmt/helpers/messages.py
pydmt/helpers/misc.py
pydmt/helpers/pkgs.py
pydmt/helpers/project.py
pydmt/helpers/python.py
pydmt/helpers/signature.py
pydmt/helpers/snipplets.py
pydmt/helpers/urls.py
pydmt/utils/__init__.py
pydmt/utils/digest.py
pydmt/utils/digester.py
pydmt/utils/filesystem.py
pydmt/utils/importlib.py
pydmt/utils/logging.py
pydmt/utils/php.py
pydmt/utils/python.py
pydmt/utils/subprocess.py
pydmt-0.3.32.dist-info/METADATA
pydmt-0.3.32.dist-info/WHEEL
pydmt-0.3.32.dist-info/entry_points.txt
pydmt-0.3.32.dist-info/licenses/LICENSE
pydmt-0.3.32.dist-info/RECORD
