Metadata-Version: 2.4
Name: pydmt
Version: 0.3.32
Summary: Python dependency management tool
Project-URL: Homepage, https://github.com/veltzer/pydmt
Project-URL: Bug Tracker, https://github.com/veltzer/pydmt/issues
Project-URL: Documentation, https://veltzer.github.io/pydmt
Project-URL: Download, https://pypi.org/project/pydmt/
Project-URL: Repository, https://github.com/veltzer/pydmt
Author-email: Mark Veltzer <mark.veltzer@gmail.com>
Maintainer-email: Mark Veltzer <mark.veltzer@gmail.com>
License-Expression: MIT
License-File: LICENSE
Keywords: cmake,cons,make,maven,mvn,pydmt,scons,software-construction
Classifier: Development Status :: 4 - Beta
Classifier: Environment :: Console
Classifier: License :: OSI Approved :: MIT License
Classifier: Operating System :: OS Independent
Classifier: Programming Language :: Python
Classifier: Programming Language :: Python :: 3
Classifier: Programming Language :: Python :: 3 :: Only
Classifier: Programming Language :: Python :: 3.12
Classifier: Topic :: Utilities
Requires-Python: >=3.12
Requires-Dist: gitpython
Requires-Dist: jsonschema
Requires-Dist: mako
Requires-Dist: pyfakeuse
Requires-Dist: pylogconf
Requires-Dist: pytconf
Requires-Dist: pyyaml
Requires-Dist: sphinx
Requires-Dist: venv-run
